pytest_cqase/__init__.py
pytest_cqase/conftest.py
pytest_cqase/plugin.py
pytest_cqase/singltone_like.py
pytest_cqase-0.1.12.dist-info/entry_points.txt
pytest_cqase-0.1.12.dist-info/LICENSE
pytest_cqase-0.1.12.dist-info/WHEEL
pytest_cqase-0.1.12.dist-info/METADATA
pytest_cqase-0.1.12.dist-info/RECORD
