Metadata-Version: 2.1
Name: pytest-cqase
Version: 0.1.12
Summary: Custom qase pytest plugin
Home-page: https://github.com/berpress/cqase-pytest
Author: alexanderlozovoy
Author-email: berpress@gmail.com
Requires-Python: >=3.8,<4.0
Classifier: Programming Language :: Python :: 3
Classifier: Programming Language :: Python :: 3.10
Classifier: Programming Language :: Python :: 3.8
Classifier: Programming Language :: Python :: 3.9
Requires-Dist: cqase-client (>=0.1.1,<0.2.0)
Requires-Dist: filelock (>=3.8.0,<4.0.0)
Requires-Dist: pytest (>=7.1.2,<8.0.0)
Project-URL: Repository, https://github.com/berpress/cqase-pytest
